{
  "collectionName": "components_utils_personnes",
  "info": {
    "displayName": "personne",
    "description": ""
  },
  "options": {},
  "attributes": {
    "textUn": {
      "type": "string"
    },
    "textDeux": {
      "type": "string"
    },
    "textUnChecked": {
      "type": "boolean",
      "default": false
    },
    "textDeuxChecked": {
      "type": "boolean",
      "default": false
    },
    "titre": {
      "type": "richtext"
    },
    "inputNom": {
      "type": "string"
    },
    "inputPrenom": {
      "type": "string"
    },
    "inputMail": {
      "type": "string"
    },
    "placeholderNom": {
      "type": "string"
    },
    "placeholderPrenom": {
      "type": "string"
    },
    "placeholderMail": {
      "type": "string"
    },
    "icon": {
      "type": "media",
      "multiple": true,
      "required": false,
      "allowedTypes": [
        "images"
      ]
    },
    "errorMessage": {
      "type": "string"
    },
    "errorMessageInputNom": {
      "type": "string"
    },
    "errorMessageInputPrenom": {
      "type": "string"
    },
    "errorMessageInputMail": {
      "type": "string"
    },
    "errorMessageInputMailRegex": {
      "type": "string"
    },
    "inputMessage": {
      "type": "text"
    },
    "errorMessageInputMessage": {
      "type": "string"
    },
    "placeholderMessage": {
      "type": "string"
    }
  }
}
